text_mining/__init__.py
text_mining/text_min.py
text_ming_group-1.0.0.dist-info/METADATA
text_ming_group-1.0.0.dist-info/WHEEL
text_ming_group-1.0.0.dist-info/top_level.txt
text_ming_group-1.0.0.dist-info/RECORD
