Metadata-Version: 2.1
Name: text-ming-group
Version: 1.0.0
Summary: categoriza registros
Author: Omar Paucar Bautista
Author-email: aryan.opb@gmail.com
